gen_tb/__init__.py
gen_tb/gen_tb.cp311-win_amd64.pyd
gen_tb/gen_tb.cp312-win_amd64.pyd
gen_tb/gen_testbench_example.py
gen_tb-1.0.dist-info/LICENSE
gen_tb-1.0.dist-info/METADATA
gen_tb-1.0.dist-info/WHEEL
gen_tb-1.0.dist-info/top_level.txt
gen_tb-1.0.dist-info/RECORD
