Metadata-Version: 2.1
Name: gen_tb
Version: 1.0
Summary: generate verilog module testbench
Home-page: https://gitee.com/Aisha-2021/gen_tb/
Author: JinSha
Author-email: jinsha2022@foxmail.com
Classifier: Programming Language :: Python :: 3.12
Classifier: License :: OSI Approved :: MIT License
Classifier: Operating System :: OS Independent
License-File: LICENSE
